{
"type": "FeatureCollection",
"crs": { "type": "name", "properties": { "name": "urn:ogc:def:crs:OGC:1.3:CRS84" } },
"features": [
{ "type": "Feature", "properties": { "name": "yellow-buoy", "date": "7-11-2020", "time": "10:00", "tideHeightFt": 10.0, "tideHeightTargetFt": 6.0, "pointDepthAdjustmentFt": -4, "depthReadingFt": 42.0, "depthAdjustedFt": 38.0, "distanceToRefPtFt": 192, "lineHeadingDeg": 145, "magneticDeclinationDeg": -16, "lineHeadingAdjustedDeg": 129, "refPointUTMEasting19T": 654743.65, "refPointUTMNorthing19T": 4999565.91, "description": "Closest yellow buoy" }, "geometry": { "type": "Point", "coordinates": [ -67.031522742763826, 45.132269281744897 ] } }
]
}
